rest_framework_supertest/__init__.py
rest_framework_supertest/settings.py
rest_framework_supertest/test.py
rest_framework_supertest/authentication/__init__.py
rest_framework_supertest/authentication/base.py
rest_framework_supertest/authentication/session.py
rest_framework_supertest/authentication/simple_jwt.py
rest_framework_supertest/mixins/__init__.py
rest_framework_supertest/mixins/authentication.py
rest_framework_supertest/mixins/exception.py
rest_framework_supertest/mixins/pagination.py
rest_framework_supertest/mixins/response.py
rest_framework_supertest/mixins/serializer.py
rest_framework_supertest/mixins/validation.py
rest_framework_supertest/models/__init__.py
rest_framework_supertest/models/base.py
rest_framework_supertest/models/decorators.py
rest_framework_supertest/models/helpers.py
rest_framework_supertest/shortcuts/__init__.py
rest_framework_supertest/shortcuts/_utils.py
rest_framework_supertest/shortcuts/addresses.py
rest_framework_supertest/shortcuts/automotives.py
rest_framework_supertest/shortcuts/colors.py
rest_framework_supertest/shortcuts/credit_cards.py
rest_framework_supertest/shortcuts/currencies.py
rest_framework_supertest/shortcuts/dates.py
rest_framework_supertest/shortcuts/emojis.py
rest_framework_supertest/shortcuts/files.py
rest_framework_supertest/shortcuts/geographicals.py
rest_framework_supertest/shortcuts/internet.py
rest_framework_supertest/shortcuts/isbn.py
rest_framework_supertest/shortcuts/jobs.py
rest_framework_supertest/shortcuts/lorem.py
rest_framework_supertest/shortcuts/misc.py
rest_framework_supertest/shortcuts/persons.py
rest_framework_supertest/shortcuts/phone_numbers.py
rest_framework_supertest/shortcuts/related.py
rest_framework_supertest/shortcuts/typing.py
rest_framework_supertest/utils/__init__.py
rest_framework_supertest/utils/exceptions.py
rest_framework_supertest/utils/faker/__init__.py
rest_framework_supertest/utils/faker/initializer.py
rest_framework_supertest/utils/faker/providers.py
django_rest_framework_supertest-0.0.6.dist-info/LICENSE
django_rest_framework_supertest-0.0.6.dist-info/METADATA
django_rest_framework_supertest-0.0.6.dist-info/WHEEL
django_rest_framework_supertest-0.0.6.dist-info/top_level.txt
django_rest_framework_supertest-0.0.6.dist-info/RECORD
