Metadata-Version: 2.1
Name: django-rest-framework-supertest
Version: 0.0.6
Summary: A set of utilities to test django-rest-framework API's
Author-email: Eduardo Oliveira <eduardo_y05@outlook.com>
Maintainer-email: Eduardo Oliveira <eduardo_y05@outlook.com>
License: MIT License
Project-URL: homepage, https://github.com/inventare/django-rest-framework-supertest/
Project-URL: documentation, https://inventare.github.io/django-rest-framework-supertest/
Keywords: django,rest,rest_framework,drf,test
Classifier: Development Status :: 5 - Production/Stable
Classifier: Environment :: Web Environment
Classifier: Framework :: Django
Classifier: Intended Audience :: Developers
Classifier: License :: OSI Approved :: MIT License
Classifier: Operating System :: OS Independent
Classifier: Programming Language :: Python
Classifier: Programming Language :: Python :: 3
Classifier: Programming Language :: Python :: 3.8
Classifier: Programming Language :: Python :: 3.9
Classifier: Programming Language :: Python :: 3.10
Classifier: Programming Language :: Python :: 3.11
Classifier: Programming Language :: Python :: 3.12
Requires-Python: >=3.8
License-File: LICENSE
Requires-Dist: Django >=4.2
Requires-Dist: djangorestframework
Requires-Dist: Faker
Provides-Extra: dev
Requires-Dist: black ; extra == 'dev'
Requires-Dist: isort ; extra == 'dev'
Requires-Dist: pre-commit ; extra == 'dev'
Provides-Extra: docs
Requires-Dist: mkdocs ; extra == 'docs'
Requires-Dist: mkdocs-material ; extra == 'docs'
Requires-Dist: mkdocs-glightbox ; extra == 'docs'
Requires-Dist: mkdocs-awesome-pages-plugin ; extra == 'docs'
Provides-Extra: image
Requires-Dist: Pillow ; extra == 'image'
Provides-Extra: jwt
Requires-Dist: djangorestframework-simplejwt ; extra == 'jwt'
Provides-Extra: test
Requires-Dist: coverage ; extra == 'test'
Requires-Dist: coveralls ; extra == 'test'
